__init__.py
cli.py
develop.py
electronic_engineering.py
ElectronicEngineering-0.1.0.dist-info/AUTHORS.rst
ElectronicEngineering-0.1.0.dist-info/LICENSE
ElectronicEngineering-0.1.0.dist-info/METADATA
ElectronicEngineering-0.1.0.dist-info/WHEEL
ElectronicEngineering-0.1.0.dist-info/top_level.txt
ElectronicEngineering-0.1.0.dist-info/RECORD
