Metadata-Version: 2.1
Name: ElectronicEngineering
Version: 0.1.0
Summary: RF/EM formulas and ...
Author-email: David Lutton <david@dalun.space>
Project-URL: Homepage, https://github.com/DavidLutton/ElectronicEngineering
Project-URL: Bug Tracker, https://github.com/DavidLutton/ElectronicEngineering/issues
Classifier: Programming Language :: Python :: 3
Classifier: License :: OSI Approved :: MIT License
Classifier: Operating System :: OS Independent
Requires-Python: >=3.7
License-File: LICENSE
License-File: AUTHORS.rst
